{
    "/admin/desktop/js/app.js": "/admin/desktop/js/app.js?id=6da9faf22cd1138284ea",
    "/admin/mobile/js/app.js": "/admin/mobile/js/app.js?id=cc0f4e804a1222063834",
    "/front/desktop/js/app.js": "/front/desktop/js/app.js?id=c4813db02cdfe152a9eb",
    "/front/mobile/js/app.js": "/front/mobile/js/app.js?id=68e13fbb0012cbb3d1c7",
    "/front/mobile/css/app.css": "/front/mobile/css/app.css?id=02195a102ed0816aa573",
    "/front/desktop/css/app.css": "/front/desktop/css/app.css?id=59f12e40a72cae714f2f",
    "/admin/mobile/css/app.css": "/admin/mobile/css/app.css?id=b5c85670393180f1843a",
    "/admin/desktop/css/app.css": "/admin/desktop/css/app.css?id=0ddd59fc131c31541d84"
}
